ShockPy/__init__.py
ShockPy/shock_wave_compression/BackwardPropagationFromWindow.py
ShockPy/shock_wave_compression/ShockWaveExperiment.py
ShockPy/shock_wave_compression/__init__.py
ShockPy/shock_wave_compression/material_database/Kapton.py
ShockPy/shock_wave_compression/material_database/MgO.py
ShockPy/shock_wave_compression/material_database/Quartz.py
ShockPy/shock_wave_compression/material_database/__init__.py
ShockPy/shock_wave_compression/material_database/baseclass/Material.py
ShockPy/shock_wave_compression/material_database/baseclass/__init__.py
ShockPy/shock_wave_compression/material_database/data/__init__.py
ShockPy/shock_wave_compression/material_states/Hugoniot.py
ShockPy/shock_wave_compression/material_states/Intersection.py
ShockPy/shock_wave_compression/material_states/Isentrope.py
ShockPy/shock_wave_compression/material_states/__init__.py
ShockPy/shock_wave_compression/material_states/isentrope_calculators/IntegratedIsentrope.py
ShockPy/shock_wave_compression/material_states/isentrope_calculators/ReflectedHugoniot.py
ShockPy/shock_wave_compression/material_states/isentrope_calculators/__init__.py
ShockPy-0.1.58.dist-info/METADATA
ShockPy-0.1.58.dist-info/WHEEL
ShockPy-0.1.58.dist-info/top_level.txt
ShockPy-0.1.58.dist-info/RECORD
