Metadata-Version: 2.1
Name: ShockPy
Version: 0.1.58
Summary: Code developed to analytically model shock wave experiments with uncertainty
Home-page: https://github.com/dimtsap/MSEE_MgO_UQ
Author: Dimitris Tsapetis
License: MIT
Platform: OSX
Platform: Windows
Platform: Linux
Classifier: Programming Language :: Python :: 3
Classifier: License :: OSI Approved :: MIT License
Classifier: Natural Language :: English
Requires-Dist: UQpy
Requires-Dist: shapely
Requires-Dist: seaborn
Provides-Extra: dev
Requires-Dist: Sphinx ; extra == 'dev'
Requires-Dist: sphinx-rtd-theme ; extra == 'dev'
Requires-Dist: sphinxcontrib-bibtex ; extra == 'dev'
Requires-Dist: sphinx-gallery ; extra == 'dev'
